wsjtx_srv/Version.py
wsjtx_srv/__init__.py
wsjtx_srv/wsjtx.py
wsjtx_srv-0.6.dist-info/LICENSE
wsjtx_srv-0.6.dist-info/METADATA
wsjtx_srv-0.6.dist-info/WHEEL
wsjtx_srv-0.6.dist-info/entry_points.txt
wsjtx_srv-0.6.dist-info/top_level.txt
wsjtx_srv-0.6.dist-info/RECORD
