Metadata-Version: 2.1
Name: wsjtx-srv
Version: 0.6
Summary: Library implementation of WSJTX companion program
Home-page: https://github.com/schlatterbeck/wsjtx-srv
Author: Ralf Schlatterbeck
Author-email: Ralf Schlatterbeck <rsc@runtux.com>
License: BSD License
Project-URL: Homepage, https://github.com/schlatterbeck/wsjtx-srv
Project-URL: Bug Tracker, https://github.com/schlatterbeck/wsjtx-srv/issues
Platform: Any
Classifier: Development Status :: 5 - Production/Stable
Classifier: License :: OSI Approved :: BSD License
Classifier: Operating System :: OS Independent
Classifier: Programming Language :: Python
Classifier: Intended Audience :: Developers
Classifier: Programming Language :: Python :: 3.7
Classifier: Programming Language :: Python :: 3.8
Classifier: Programming Language :: Python :: 3.9
Classifier: Programming Language :: Python :: 3.10
Classifier: Programming Language :: Python :: 3.11
Requires-Python: >=3.7
License-File: LICENSE
Requires-Dist: rsclib
Requires-Dist: hamradio
